coalestr/__init__.py
coalestr/cs.py
coalestr-0.2.17.dist-info/LICENSE
coalestr-0.2.17.dist-info/METADATA
coalestr-0.2.17.dist-info/WHEEL
coalestr-0.2.17.dist-info/top_level.txt
coalestr-0.2.17.dist-info/RECORD
