Metadata-Version: 2.1
Name: coalestr
Version: 0.2.17
Summary: A Python package for implementing the genomic transmission graph
Author: Dominic Kwiatkowski
Author-email: <dkwiatkowski@sjc.ox.ac.uk>
Keywords: python,first package
Classifier: Development Status :: 3 - Alpha
Classifier: Intended Audience :: Education
Classifier: Programming Language :: Python :: 2
Classifier: Programming Language :: Python :: 3
Classifier: Operating System :: MacOS :: MacOS X
Classifier: Operating System :: Microsoft :: Windows
License-File: LICENSE
Requires-Dist: numpy
Requires-Dist: matplotlib
